{
  "project_info": {
    "project_number": "516183083158",
    "firebase_url": "https://authentication-8ea60-default-rtdb.firebaseio.com",
    "project_id": "authentication-8ea60",
    "storage_bucket": "authentication-8ea60.appspot.com"
  },
  "client": [
    {
      "client_info": {
        "mobilesdk_app_id": "1:516183083158:android:56e5cc5eec802f70725ab7",
        "android_client_info": {
          "package_name": "com.example.chatappfirebaserealtimedatabase"
        }
      },
      "oauth_client": [
        {
          "client_id": "516183083158-6fu8nam8jaim69qhbd5ped00reoja4ma.apps.googleusercontent.com",
          "client_type": 1,
          "android_info": {
            "package_name": "com.example.chatappfirebaserealtimedatabase",
            "certificate_hash": "f3bcdedc50d7f9cfd4b2a04e6f10761c02f158f8"
          }
        },
        {
          "client_id": "516183083158-pmcu3kpab7kj03k79o5efbbi63147h09.apps.googleusercontent.com",
          "client_type": 3
        }
      ],
      "api_key": [
        {
          "current_key": "AIzaSyC1USK6nt0tSh8mXkPQq8EVWpT6Qgi7Hkg"
        }
      ],
      "services": {
        "appinvite_service": {
          "other_platform_oauth_client": [
            {
              "client_id": "516183083158-pmcu3kpab7kj03k79o5efbbi63147h09.apps.googleusercontent.com",
              "client_type": 3
            }
          ]
        }
      }
    },
    {
      "client_info": {
        "mobilesdk_app_id": "1:516183083158:android:75ea2454a34ba7e5725ab7",
        "android_client_info": {
          "package_name": "com.example.firebaseauth"
        }
      },
      "oauth_client": [
        {
          "client_id": "516183083158-nu1utprk2vot7he8nmh7fd85isatf4jc.apps.googleusercontent.com",
          "client_type": 1,
          "android_info": {
            "package_name": "com.example.firebaseauth",
            "certificate_hash": "f3bcdedc50d7f9cfd4b2a04e6f10761c02f158f8"
          }
        },
        {
          "client_id": "516183083158-pmcu3kpab7kj03k79o5efbbi63147h09.apps.googleusercontent.com",
          "client_type": 3
        }
      ],
      "api_key": [
        {
          "current_key": "AIzaSyC1USK6nt0tSh8mXkPQq8EVWpT6Qgi7Hkg"
        }
      ],
      "services": {
        "appinvite_service": {
          "other_platform_oauth_client": [
            {
              "client_id": "516183083158-pmcu3kpab7kj03k79o5efbbi63147h09.apps.googleusercontent.com",
              "client_type": 3
            }
          ]
        }
      }
    },
    {
      "client_info": {
        "mobilesdk_app_id": "1:516183083158:android:2e49a0344170800c725ab7",
        "android_client_info": {
          "package_name": "com.example.firebasedbpaging"
        }
      },
      "oauth_client": [
        {
          "client_id": "516183083158-pmcu3kpab7kj03k79o5efbbi63147h09.apps.googleusercontent.com",
          "client_type": 3
        }
      ],
      "api_key": [
        {
          "current_key": "AIzaSyC1USK6nt0tSh8mXkPQq8EVWpT6Qgi7Hkg"
        }
      ],
      "services": {
        "appinvite_service": {
          "other_platform_oauth_client": [
            {
              "client_id": "516183083158-pmcu3kpab7kj03k79o5efbbi63147h09.apps.googleusercontent.com",
              "client_type": 3
            }
          ]
        }
      }
    },
    {
      "client_info": {
        "mobilesdk_app_id": "1:516183083158:android:4b338bf049ed3bc5725ab7",
        "android_client_info": {
          "package_name": "com.example.firebaseui"
        }
      },
      "oauth_client": [
        {
          "client_id": "516183083158-pmcu3kpab7kj03k79o5efbbi63147h09.apps.googleusercontent.com",
          "client_type": 3
        }
      ],
      "api_key": [
        {
          "current_key": "AIzaSyC1USK6nt0tSh8mXkPQq8EVWpT6Qgi7Hkg"
        }
      ],
      "services": {
        "appinvite_service": {
          "other_platform_oauth_client": [
            {
              "client_id": "516183083158-pmcu3kpab7kj03k79o5efbbi63147h09.apps.googleusercontent.com",
              "client_type": 3
            }
          ]
        }
      }
    },
    {
      "client_info": {
        "mobilesdk_app_id": "1:516183083158:android:ccf02266984af7ee725ab7",
        "android_client_info": {
          "package_name": "com.example.firestore"
        }
      },
      "oauth_client": [
        {
          "client_id": "516183083158-pmcu3kpab7kj03k79o5efbbi63147h09.apps.googleusercontent.com",
          "client_type": 3
        }
      ],
      "api_key": [
        {
          "current_key": "AIzaSyC1USK6nt0tSh8mXkPQq8EVWpT6Qgi7Hkg"
        }
      ],
      "services": {
        "appinvite_service": {
          "other_platform_oauth_client": [
            {
              "client_id": "516183083158-pmcu3kpab7kj03k79o5efbbi63147h09.apps.googleusercontent.com",
              "client_type": 3
            }
          ]
        }
      }
    }
  ],
  "configuration_version": "1"
}